porchestrator/__init__.py
porchestrator/notification.py
porchestrator/orchestrator.py
porchestrator/parser.py
porchestrator-0.6.0.dist-info/LICENSE
porchestrator-0.6.0.dist-info/METADATA
porchestrator-0.6.0.dist-info/WHEEL
porchestrator-0.6.0.dist-info/RECORD
