Metadata-Version: 2.1
Name: porchestrator
Version: 0.6.0
Summary: Simple Task Orchestrator using Prefect
License: MIT
Author: Jayasimha Raghavan
Author-email: mr.jayasimha@gmail.com
Requires-Python: >=3.12,<4.0
Classifier: License :: OSI Approved :: MIT License
Classifier: Programming Language :: Python :: 3
Classifier: Programming Language :: Python :: 3.12
Requires-Dist: boto3 (>=1.21.7,<2.0.0)
Requires-Dist: loguru (>=0.7.2,<0.8.0)
Requires-Dist: prefect (>=2.19.7,<3.0.0)
Requires-Dist: pyyaml (>=6.0,<7.0)
Requires-Dist: sendgrid (>=6.11.0,<7.0.0)
